README.md
setup.cfg
setup.py
calmsize/__init__.py
calmsize/calmsize.py
calmsize.egg-info/PKG-INFO
calmsize.egg-info/SOURCES.txt
calmsize.egg-info/dependency_links.txt
calmsize.egg-info/requires.txt
calmsize.egg-info/top_level.txt
calmsize.egg-info/zip-safe
test/test_basic.py
test/test_doc.py