Metadata-Version: 2.1
Name: calmsize
Version: 0.1.1
Summary: Fork from hurry.filesize, A simple Python library for human readable file sizes (or anything sized in bytes).
Home-page: https://github.com/Stonesjtu/calmsize
Author: Kaiyu Shi
Author-email: skyisno.1@gmail.com
License: ZPL 2.1
Keywords: file size bytes
Platform: UNKNOWN
Classifier: Programming Language :: Python
Classifier: Topic :: Software Development :: Libraries :: Python Modules
